setup.py
deploy/__init__.py
deploy/conf.py
deploy/models.py
deploy.egg-info/PKG-INFO
deploy.egg-info/SOURCES.txt
deploy.egg-info/dependency_links.txt
deploy.egg-info/top_level.txt
deploy/bin/deploy
deploy/bin/deploy-init
deploy/bin/deploy-remove
deploy/bin/deploy-restart
deploy/bin/deploy-serverconf
deploy/bin/deploy-startserver