Metadata-Version: 1.0
Name: deploy
Version: 1.9.1
Summary: Easy deploy Python WSGI apps
Home-page: https://github.com/ondrejsika/deploy
Author: Ondrej Sika
Author-email: ondrej@ondrejsika.com
License: MIT
Platform: UNKNOWN
